pggo/__init__.py
pggo/_binding.py
pggo/dbapi.py
pggo/libpggo.so
pggo-1.2.0.dist-info/licenses/LICENSE
pggo-1.2.0.dist-info/METADATA
pggo-1.2.0.dist-info/WHEEL
pggo-1.2.0.dist-info/top_level.txt
pggo-1.2.0.dist-info/RECORD
