Metadata-Version: 2.4
Name: pggo
Version: 1.2.0
Summary: A PostgreSQL driver written in Golang for Python
Author-email: Lucas Lima Fernandes <lucas.lfernandes@live.com>
License-Expression: MIT
Project-URL: Homepage, https://github.com/lucaslimafernandes/pggo
Project-URL: Issues, https://github.com/lucaslimafernandes/pggo/issues
Classifier: Programming Language :: Python :: 3
Classifier: Programming Language :: Python :: 3.9
Classifier: Programming Language :: Python :: 3.10
Classifier: Programming Language :: Python :: 3.11
Classifier: Programming Language :: Python :: 3.12
Classifier: Operating System :: POSIX :: Linux
Classifier: Operating System :: MacOS
Classifier: Operating System :: Microsoft :: Windows
Classifier: Programming Language :: Python
Requires-Python: >=3.9
License-File: LICENSE
Dynamic: license-file
Dynamic: requires-python
